pyroll/lippmann_mahrenholz_power_and_labour.py
pyroll_lippmann_mahrenholz_power_and_labour-2.0.0.dist-info/METADATA
pyroll_lippmann_mahrenholz_power_and_labour-2.0.0.dist-info/WHEEL
pyroll_lippmann_mahrenholz_power_and_labour-2.0.0.dist-info/licenses/LICENSE
pyroll_lippmann_mahrenholz_power_and_labour-2.0.0.dist-info/RECORD
