Metadata-Version: 2.1
Name: pyroll-lippmann-mahrenholz-power-and-labour
Version: 2.0.0
Summary: Plugin for PyRolL providing the power and labour calculation after O. Lippmann and H. Mahrenholz
Author-email: Christoph Renzing <christoph.renzing@imf.tu-freiberg.de>
License-Expression: BSD-3-Clause
License-File: LICENSE
Classifier: Intended Audience :: Manufacturing
Classifier: Intended Audience :: Science/Research
Classifier: Operating System :: OS Independent
Classifier: Topic :: Scientific/Engineering
Requires-Python: <4.0,>=3.9
Requires-Dist: pyroll-core
